nonebot_plugin_mc_server_status/__init__.py
nonebot_plugin_mc_server_status/config.py
nonebot_plugin_mc_server_status-0.4.1.dist-info/METADATA
nonebot_plugin_mc_server_status-0.4.1.dist-info/WHEEL
nonebot_plugin_mc_server_status-0.4.1.dist-info/RECORD
